<clientscript scriptid="customscript_mx_plus_autollenado_cs">
  <description>Llena en automático los datos de cliente (forma de pago, método de pago, uso de cfdi y plantilla de facturación) en transacciones de factura de venta, pago de cliente y nota de crédito.</description>
  <isinactive>F</isinactive>
  <name>MX+ Autollenado Datos - CS</name>
  <notifyadmins>F</notifyadmins>
  <notifyemails></notifyemails>
  <notifyowner>T</notifyowner>
  <notifyuser>F</notifyuser>
  <scriptfile>[/SuiteScripts/MX+ 2024/Utilities/MX_PLUS_AUTOLLENADO_CS.js]</scriptfile>
  <scriptdeployments>
    <scriptdeployment scriptid="customdeploy_mx_plus_autollenado_credito">
      <allemployees>T</allemployees>
      <alllocalizationcontexts>T</alllocalizationcontexts>
      <allpartners>F</allpartners>
      <allroles>T</allroles>
      <audslctrole></audslctrole>
      <audsubsidiary>[ACCOUNT_SPECIFIC_VALUE]|[ACCOUNT_SPECIFIC_VALUE]|[ACCOUNT_SPECIFIC_VALUE]</audsubsidiary>
      <eventtype></eventtype>
      <executioncontext>ACTION|ADVANCEDREVREC|BANKCONNECTIVITY|BANKSTATEMENTPARSER|BUNDLEINSTALLATION|CLIENT|CONSOLRATEADJUSTOR|CSVIMPORT|CUSTOMGLLINES|CUSTOMMASSUPDATE|DATASETBUILDER|DEBUGGER|EMAILCAPTURE|FICONNECTIVITY|FIPARSER|MAPREDUCE|OCRPLUGIN|OTHER|PAYMENTGATEWAY|PAYMENTPOSTBACK|PLATFORMEXTENSION|PORTLET|PROMOTIONS|RECORDACTION|RESTLET|RESTWEBSERVICES|SCHEDULED|SDFINSTALLATION|SHIPPINGPARTNERS|SUITELET|TAXCALCULATION|USEREVENT|USERINTERFACE|WEBSERVICES|WORKBOOKBUILDER|WORKFLOW</executioncontext>
      <isdeployed>T</isdeployed>
      <loglevel>DEBUG</loglevel>
      <recordtype>CREDITMEMO</recordtype>
      <status>RELEASED</status>
    </scriptdeployment>
    <scriptdeployment scriptid="customdeploy_mx_plus_autollenado_pago">
      <allemployees>T</allemployees>
      <alllocalizationcontexts>T</alllocalizationcontexts>
      <allpartners>F</allpartners>
      <allroles>T</allroles>
      <audslctrole></audslctrole>
      <audsubsidiary>[ACCOUNT_SPECIFIC_VALUE]|[ACCOUNT_SPECIFIC_VALUE]|[ACCOUNT_SPECIFIC_VALUE]</audsubsidiary>
      <eventtype></eventtype>
      <executioncontext>ACTION|ADVANCEDREVREC|BANKCONNECTIVITY|BANKSTATEMENTPARSER|BUNDLEINSTALLATION|CLIENT|CONSOLRATEADJUSTOR|CSVIMPORT|CUSTOMGLLINES|CUSTOMMASSUPDATE|DATASETBUILDER|DEBUGGER|EMAILCAPTURE|FICONNECTIVITY|FIPARSER|MAPREDUCE|OCRPLUGIN|OTHER|PAYMENTGATEWAY|PAYMENTPOSTBACK|PLATFORMEXTENSION|PORTLET|PROMOTIONS|RECORDACTION|RESTLET|RESTWEBSERVICES|SCHEDULED|SDFINSTALLATION|SHIPPINGPARTNERS|SUITELET|TAXCALCULATION|USEREVENT|USERINTERFACE|WEBSERVICES|WORKBOOKBUILDER|WORKFLOW</executioncontext>
      <isdeployed>T</isdeployed>
      <loglevel>DEBUG</loglevel>
      <recordtype>CUSTOMERPAYMENT</recordtype>
      <status>RELEASED</status>
    </scriptdeployment>
    <scriptdeployment scriptid="customdeploy_mx_plus_autollenado_invoice">
      <allemployees>T</allemployees>
      <alllocalizationcontexts>T</alllocalizationcontexts>
      <allpartners>F</allpartners>
      <allroles>T</allroles>
      <audslctrole></audslctrole>
      <audsubsidiary>[ACCOUNT_SPECIFIC_VALUE]|[ACCOUNT_SPECIFIC_VALUE]|[ACCOUNT_SPECIFIC_VALUE]</audsubsidiary>
      <eventtype></eventtype>
      <executioncontext>ACTION|ADVANCEDREVREC|BANKCONNECTIVITY|BANKSTATEMENTPARSER|BUNDLEINSTALLATION|CLIENT|CONSOLRATEADJUSTOR|CSVIMPORT|CUSTOMGLLINES|CUSTOMMASSUPDATE|DATASETBUILDER|DEBUGGER|EMAILCAPTURE|FICONNECTIVITY|FIPARSER|MAPREDUCE|OCRPLUGIN|OTHER|PAYMENTGATEWAY|PAYMENTPOSTBACK|PLATFORMEXTENSION|PORTLET|PROMOTIONS|RECORDACTION|RESTLET|RESTWEBSERVICES|SCHEDULED|SDFINSTALLATION|SHIPPINGPARTNERS|SUITELET|TAXCALCULATION|USEREVENT|USERINTERFACE|WEBSERVICES|WORKBOOKBUILDER|WORKFLOW</executioncontext>
      <isdeployed>T</isdeployed>
      <loglevel>DEBUG</loglevel>
      <recordtype>INVOICE</recordtype>
      <status>RELEASED</status>
    </scriptdeployment>
  </scriptdeployments>
</clientscript>